datagusto/__init__.py
datagusto/callback.py
datagusto/client.py
datagusto_dev_sdk-0.1.2.dist-info/METADATA
datagusto_dev_sdk-0.1.2.dist-info/WHEEL
datagusto_dev_sdk-0.1.2.dist-info/RECORD
