Metadata-Version: 2.4
Name: datagusto-dev-sdk
Version: 0.1.2
Summary: Datagusto SDK for Python
Project-URL: Homepage, https://datagusto.ai
Author-email: Datagusto <info@datagusto.ai>
License: MIT
Classifier: Development Status :: 3 - Alpha
Classifier: Intended Audience :: Developers
Classifier: License :: OSI Approved :: MIT License
Classifier: Programming Language :: Python :: 3
Classifier: Programming Language :: Python :: 3.12
Requires-Python: >=3.12
Requires-Dist: langchain-core>=0.3.48
Requires-Dist: langchain>=0.3.21
